LICENSE
MANIFEST.in
README.rst
setup.py
ParsePkgtxt/__init__.py
ParsePkgtxt/parsepkgtxt.py
ParsePkgtxt.egg-info/PKG-INFO
ParsePkgtxt.egg-info/SOURCES.txt
ParsePkgtxt.egg-info/dependency_links.txt
ParsePkgtxt.egg-info/top_level.txt