Metadata-Version: 1.1
Name: ParsePkgtxt
Version: 0.1
Summary: Parse a Slackware PACKAGES.TXT and build a dictionnary
Home-page: http://github.com/fredg/ParsePkgtxt
Author: Frédéric Galusik
Author-email: fred.galusik at gmail
License: BSD revised
Platform: UNKNOWN
Classifier: Programming Language :: Python
Classifier: Development Status :: 4 - Beta
Classifier: License :: OSI Approved :: BSD License
Classifier: Natural Language :: English
Classifier: Operating System :: OS Independent
Classifier: Programming Language :: Python :: 2.7
Classifier: Topic :: Utilities
